asyncspawner/__init__.py
asyncspawner/logger.py
asyncspawner/spawner.py
AsyncSpawner-0.1.1.dist-info/LICENSE
AsyncSpawner-0.1.1.dist-info/METADATA
AsyncSpawner-0.1.1.dist-info/WHEEL
AsyncSpawner-0.1.1.dist-info/top_level.txt
AsyncSpawner-0.1.1.dist-info/RECORD
