Metadata-Version: 2.1
Name: AsyncSpawner
Version: 0.1.1
Summary: Spawn asyncio coroutines over threads running in multiple processes.
Home-page: https://github.com/ktolstikhin/asyncspawner
Author: Konstantin Tolstikhin
Author-email: k.tolstikhin@gmail.com
License: MIT
Classifier: License :: OSI Approved :: MIT License
Classifier: Programming Language :: Python :: 3.7
Classifier: Operating System :: OS Independent
Requires-Python: >=3.7
License-File: LICENSE
